python_pyenv_poetry_template/__init__.py
python_pyenv_poetry_template/__main__.py
python_pyenv_poetry_template/config/__init__.py
python_pyenv_poetry_template/config/config.json
python_pyenv_poetry_template/config/config.py
python_pyenv_poetry_template/info.py
python_pyenv_poetry_template/logger/__init__.py
python_pyenv_poetry_template/logger/logger.py
python_pyenv_poetry_template/main.py
python_pyenv_poetry_template-0.9.2.dist-info/LICENSE
python_pyenv_poetry_template-0.9.2.dist-info/METADATA
python_pyenv_poetry_template-0.9.2.dist-info/WHEEL
python_pyenv_poetry_template-0.9.2.dist-info/RECORD
