Metadata-Version: 2.3
Name: python_pyenv_poetry_template
Version: 0.9.2
Summary: A GitHub template for Python projects using Pyenv and Poetry
License: MIT
Author: Fabio Calefato
Author-email: fcalefato@gmail.com
Requires-Python: >=3.12,<4.0
Classifier: License :: OSI Approved :: MIT License
Classifier: Programming Language :: Python :: 3
Classifier: Programming Language :: Python :: 3.12
Classifier: Programming Language :: Python :: 3.13
Requires-Dist: pretty-errors
Requires-Dist: rich
Requires-Dist: tomlkit
Project-URL: Repository, https://github.com/bateman/python_pyenv_poetry_template
